[
  {
    "id": 0,
    "group": "property",
    "name": "Makoko",
    "price": 60,
    "color": "brown",
    "occupants": [],
    "owner": [],
    "houses": [],
    "rent": [2, 10, 30, 90, 160, 250],
    "houseCost": 50,
    "mortgageValue": 30,
    "mortgageStatus": false
  },
  {
    "id": 1,
    "group": "action",
    "type": "community"
  },
  {
    "id": 2,
    "name": "Agege",
    "group": "property",
    "price": 80,
    "color": "brown",
    "occupants": [],
    "owner": [],
    "houses": [],
    "rent": [4, 20, 60, 180, 320, 450],
    "houseCost": 50,
    "mortgageValue": 30,
    "mortgageStatus": false
  },
  {
    "id": 3,
    "group": "fee",
    "type": "income",
    "fee": 200
  },
  {
    "id": 4,
    "group": "railroad",
    "name": "Iddo Terminus",
    "price": 200,
    "occupants": [],
    "owner": [],
    "mortgageValue": 100,
    "mortgageStatus": false
  },
  {
    "id": 5,
    "group": "property",
    "name": "Opebi",
    "price": 100,
    "color": "light-blue",
    "occupants": [],
    "owner": [],
    "houses": [],
    "rent": [6, 30, 90, 270, 400, 550],
    "houseCost": 50,
    "mortgageValue": 50,
    "mortgageStatus": false
  },
  {
    "id": 6,
    "group": "action",
    "type": "chance"
  },
  {
    "id": 7,
    "group": "property",
    "name": "Ikeja",
    "price": 100,
    "color": "light-blue",
    "occupants": [],
    "owner": [],
    "houses": [],
    "rent": [6, 30, 90, 270, 400, 550],
    "houseCost": 50,
    "mortgageValue": 50,
    "mortgageStatus": false
  },
  {
    "id": 8,
    "group": "property",
    "name": "Sabo-Yaba",
    "price": 120,
    "color": "light-blue",
    "occupants": [],
    "owner": [],
    "houses": [],
    "rent": [8, 40, 100, 300, 450, 600],
    "houseCost": 50,
    "mortgageValue": 60,
    "mortgageStatus": false
  },
  {
    "id": 9,
    "group": "property",
    "name": "Palms Shopping Mall",
    "price": 140,
    "color": "purple",
    "occupants": [],
    "owner": [],
    "houses": [],
    "rent": [10, 50, 150, 450, 625, 750],
    "houseCost": 100,
    "mortgageValue": 70,
    "mortgageStatus": false
  },
  {
    "id": 10,
    "group": "utility",
    "type": "electric",
    "price": 150,
    "occupants": [],
    "owner": [],
    "mortgageValue": 75,
    "mortgageStatus": false
  },
  {
    "id": 11,
    "group": "property",
    "name": "Admirality Circle Plaza",
    "price": 140,
    "color": "purple",
    "occupants": [],
    "owner": [],
    "houses": [],
    "rent": [10, 50, 150, 450, 625, 750],
    "houseCost": 100,
    "mortgageValue": 70,
    "mortgageStatus": false
  },
  {
    "id": 12,
    "group": "property",
    "name": "Admirality Way",
    "price": 160,
    "color": "purple",
    "occupants": [],
    "owner": [],
    "houses": [],
    "rent": [12, 60, 180, 500, 700, 900],
    "houseCost": 100,
    "mortgageValue": 80,
    "mortgageStatus": false
  },
  {
    "id": 13,
    "group": "railroad",
    "name": "Tincan Island Port",
    "price": 200,
    "occupants": [],
    "owner": [],
    "mortgageValue": 100,
    "mortgageStatus": false
  },
  {
    "id": 14,
    "group": "property",
    "name": "Mansard Place",
    "price": 180,
    "color": "orange",
    "occupants": [],
    "owner": [],
    "houses": [],
    "rent": [14, 70, 200, 550, 750, 950],
    "houseCost": 100,
    "mortgageValue": 90,
    "mortgageStatus": false
  },
  {
    "id": 15,
    "group": "action",
    "type": "community"
  },
  {
    "id": 16,
    "group": "property",
    "name": "King's College",
    "price": 180,
    "color": "orange",
    "occupants": [],
    "owner": [],
    "houses": [],
    "rent": [14, 70, 200, 550, 750, 950],
    "houseCost": 100,
    "mortgageValue": 90,
    "mortgageStatus": false
  },
  {
    "id": 17,
    "group": "property",
    "name": "Awolowo Road",
    "price": 200,
    "color": "orange",
    "occupants": [],
    "owner": [],
    "houses": [],
    "rent": [16, 80, 220, 600, 800, 1000],
    "houseCost": 100,
    "mortgageValue": 100,
    "mortgageStatus": false
  },
  {
    "id": 18,
    "group": "property",
    "name": "Muson Centre",
    "price": 220,
    "color": "red",
    "occupants": [],
    "owner": [],
    "houses": [],
    "rent": [18, 90, 250, 700, 875, 1050],
    "houseCost": 150,
    "mortgageValue": 110,
    "mortgageStatus": false
  },
  {
    "id": 19,
    "group": "action",
    "type": "chance"
  },
  {
    "id": 20,
    "group": "property",
    "name": "Lagos Yacht Club",
    "price": 220,
    "color": "red",
    "occupants": [],
    "owner": [],
    "houses": [],
    "rent": [18, 90, 250, 700, 875, 1050],
    "houseCost": 150,
    "mortgageValue": 110,
    "mortgageStatus": false
  },
  {
    "id": 21,
    "group": "property",
    "name": "Tiamiyu Savage Str.",
    "price": 240,
    "color": "red",
    "occupants": [],
    "owner": [],
    "houses": [],
    "rent": [20, 100, 300, 750, 925, 1100],
    "houseCost": 150,
    "mortgageValue": 120,
    "mortgageStatus": false
  },
  {
    "id": 22,
    "group": "railroad",
    "name": "BRT Bus Terminal",
    "price": 200,
    "occupants": [],
    "owner": [],
    "mortgageValue": 100,
    "mortgageStatus": false
  },
  {
    "id": 23,
    "group": "property",
    "name": "Falomo Shopping Centre",
    "price": 260,
    "color": "yellow",
    "occupants": [],
    "owner": [],
    "houses": [],
    "rent": [22, 110, 330, 800, 975, 1150],
    "houseCost": 150,
    "mortgageValue": 130,
    "mortgageStatus": false
  },
  {
    "id": 24,
    "group": "property",
    "name": "35 Marina",
    "price": 260,
    "color": "yellow",
    "occupants": [],
    "owner": [],
    "houses": [],
    "rent": [22, 110, 330, 800, 975, 1150],
    "houseCost": 150,
    "mortgageValue": 130,
    "mortgageStatus": false
  },
  {
    "id": 24,
    "group": "utility",
    "type": "water",
    "price": 150,
    "occupants": [],
    "owner": [],
    "mortgageValue": 75,
    "mortgageStatus": false
  },
  {
    "id": 26,
    "group": "property",
    "name": "Silverbird Cinema",
    "price": 280,
    "color": "yellow",
    "occupants": [],
    "owner": [],
    "houses": [],
    "rent": [24, 120, 360, 850, 1025, 1200],
    "houseCost": 150,
    "mortgageValue": 130,
    "mortgageStatus": false
  },
  {
    "id": 27,
    "group": "property",
    "name": "Ikoyi",
    "price": 300,
    "color": "green",
    "occupants": [],
    "owner": [],
    "houses": [],
    "rent": [26, 130, 390, 900, 1100, 1275],
    "houseCost": 200,
    "mortgageValue": 150,
    "mortgageStatus": false
  },
  {
    "id": 28,
    "group": "property",
    "name": "635 Akin Adesola St.",
    "price": 300,
    "color": "green",
    "occupants": [],
    "owner": [],
    "houses": [],
    "rent": [26, 130, 390, 900, 1100, 1275],
    "houseCost": 200,
    "mortgageValue": 150,
    "mortgageStatus": false
  },
  {
    "id": 29,
    "group": "action",
    "type": "community"
  },
  {
    "id": 30,
    "group": "property",
    "name": "Ilashe Road",
    "price": 320,
    "color": "green",
    "occupants": [],
    "owner": [],
    "houses": [],
    "rent": [28, 150, 450, 1000, 1200, 1400],
    "houseCost": 200,
    "mortgageValue": 160,
    "mortgageStatus": false
  },
  {
    "id": 31,
    "group": "railroad",
    "name": "Murtala Mohammed International Airport",
    "price": 200,
    "occupants": [],
    "owner": [],
    "mortgageValue": 100,
    "mortgageStatus": false
  },
  {
    "id": 32,
    "group": "action",
    "type": "chance"
  },
  {
    "id": 33,
    "group": "property",
    "name": "Bourdillon Road",
    "price": 350,
    "color": "dark-blue",
    "occupants": [],
    "owner": [],
    "houses": [],
    "rent": [35, 175, 500, 1100, 1300, 1500],
    "houseCost": 200,
    "mortgageValue": 175,
    "mortgageStatus": false
  },
  {
    "id": 34,
    "group": "fee",
    "type": "luxury",
    "fee": 100
  },
  {
    "id": 35,
    "group": "property",
    "name": "Banana Island",
    "price": 400,
    "color": "dark-blue",
    "occupants": [],
    "owner": [],
    "houses": [],
    "rent": [50, 200, 600, 1400, 1700, 2000],
    "houseCost": 200,
    "mortgageValue": 200,
    "mortgageStatus": false
  }
]
